helmkit/__init__.py
helmkit/molecule.py
helmkit/py.typed
helmkit/data/monomers.sdf
helmkit-0.7.0.dist-info/METADATA
helmkit-0.7.0.dist-info/WHEEL
helmkit-0.7.0.dist-info/licenses/LICENSE
helmkit-0.7.0.dist-info/RECORD
