Metadata-Version: 2.4
Name: helmkit
Version: 0.7.0
Summary: Parse HELM strings into RDKit molecules
License-File: LICENSE
Requires-Python: >=3.11
Requires-Dist: rdkit>=2025.3.3
